mw_jinja2/__init__.py
mw_jinja2/_compat.py
mw_jinja2/_identifier.py
mw_jinja2/asyncfilters.py
mw_jinja2/asyncsupport.py
mw_jinja2/bccache.py
mw_jinja2/compiler.py
mw_jinja2/constants.py
mw_jinja2/debug.py
mw_jinja2/defaults.py
mw_jinja2/environment.py
mw_jinja2/exceptions.py
mw_jinja2/ext.py
mw_jinja2/filters.py
mw_jinja2/idtracking.py
mw_jinja2/lexer.py
mw_jinja2/loaders.py
mw_jinja2/meta.py
mw_jinja2/nativetypes.py
mw_jinja2/nodes.py
mw_jinja2/optimizer.py
mw_jinja2/parser.py
mw_jinja2/runtime.py
mw_jinja2/sandbox.py
mw_jinja2/tests.py
mw_jinja2/utils.py
mw_jinja2/visitor.py
mw_jinja2-2.11.3.dist-info/LICENSE.rst
mw_jinja2-2.11.3.dist-info/METADATA
mw_jinja2-2.11.3.dist-info/WHEEL
mw_jinja2-2.11.3.dist-info/entry_points.txt
mw_jinja2-2.11.3.dist-info/top_level.txt
mw_jinja2-2.11.3.dist-info/RECORD
